executor_s3_backend/__init__.py
executor_s3_backend/_config.py
executor_s3_backend/install.py
executor_s3_backend/serve.py
executor_s3_backend-0.0.1.dist-info/METADATA
executor_s3_backend-0.0.1.dist-info/WHEEL
executor_s3_backend-0.0.1.dist-info/top_level.txt
executor_s3_backend-0.0.1.dist-info/RECORD
