Metadata-Version: 2.1
Name: executor-s3-backend
Version: 0.0.1
Summary: DaggerML's backend for executor-s3
Author-email: DaggerML <engineering@daggerml.com>
Project-URL: Homepage, https://daggerml.com
Project-URL: Documentation, https://daggerml.com/docs
Project-URL: Issues, https://github.com/daggerml/executor-s3-backend/issues
Classifier: Operating System :: OS Independent
Classifier: Development Status :: 4 - Beta
Classifier: Programming Language :: Python :: 3
Classifier: Programming Language :: Python :: 3.6
Classifier: Programming Language :: Python :: 3.7
Classifier: Programming Language :: Python :: 3.8
Classifier: Programming Language :: Python :: 3.9
Classifier: Programming Language :: Python :: 3.10
Classifier: Programming Language :: Python :: 3.11
Requires-Python: >=3.6
Requires-Dist: daggerml (==0.0.3)
Requires-Dist: boto3
Requires-Dist: requests
Requires-Dist: fastapi
Requires-Dist: uvicorn[standard]
Requires-Dist: python-multipart
